dolfin_navier_scipy/__init__.py
dolfin_navier_scipy/cache_simustates_utils.py
dolfin_navier_scipy/data_output_utils.py
dolfin_navier_scipy/dolfin_to_sparrays.py
dolfin_navier_scipy/problem_setups.py
dolfin_navier_scipy/residual_checks.py
dolfin_navier_scipy/stokes_navier_utils.py
dolfin_navier_scipy/time_int_utils.py
dolfin_navier_scipy/time_step_schemes.py
dolfin_navier_scipy-1.4.1.dist-info/AUTHORS
dolfin_navier_scipy-1.4.1.dist-info/LICENSE.md
dolfin_navier_scipy-1.4.1.dist-info/METADATA
dolfin_navier_scipy-1.4.1.dist-info/WHEEL
dolfin_navier_scipy-1.4.1.dist-info/pbr.json
dolfin_navier_scipy-1.4.1.dist-info/top_level.txt
dolfin_navier_scipy-1.4.1.dist-info/RECORD
