Metadata-Version: 2.1
Name: dolfin-navier-scipy
Version: 1.4.1
Summary: A Scipy-Fenics interface for incompressible Navier-Stokes
Home-page: https://github.com/highlando/dolfin_navier_scipy
Author: Jan Heiland
Author-email: jnhlnd@gmail.com
Maintainer: Jan Heiland
Maintainer-email: jnhlnd@gmail.com
License: GPLv3
Platform: UNKNOWN
Classifier: License :: OSI Approved :: BSD License
Classifier: Operating System :: OS Independent
Classifier: Programming Language :: Python
Classifier: Programming Language :: Python :: 2.7
Classifier: Programming Language :: Python :: 3
Classifier: License :: OSI Approved :: GNU General Public License v3 (GPLv3)
License-File: LICENSE.md
License-File: AUTHORS
Requires-Dist: numpy
Requires-Dist: pbr
Requires-Dist: rich
Requires-Dist: sadptprj-riclyap-adi
Requires-Dist: scipy
Requires-Dist: setuptools
